producthunt/__init__.py
producthunt/producthunt.py
producthunt-0.1.4.dist-info/METADATA
producthunt-0.1.4.dist-info/WHEEL
producthunt-0.1.4.dist-info/top_level.txt
producthunt-0.1.4.dist-info/RECORD
