Metadata-Version: 2.1
Name: producthunt
Version: 0.1.4
Summary: A Python wrapper on Product Hunt API
Author: Dariush Abbasi
Author-email: poshtehani@gmail.com
License: MIT
Classifier: License :: OSI Approved :: MIT License
Classifier: Programming Language :: Python :: 3
Classifier: Programming Language :: Python :: 3.6
Classifier: Programming Language :: Python :: 3.7
Classifier: Programming Language :: Python :: 3.8
Classifier: Programming Language :: Python :: 3.9
